CHANGELOG
MANIFEST.in
README.md
setup.py
lsl_toolkits/__init__.py
lsl_toolkits/OldDRSpec/__init__.py
lsl_toolkits/OldDRSpec/oldfast.c
lsl_toolkits/OldDRSpec/reader.py
lsl_toolkits_olddrspec.egg-info/PKG-INFO
lsl_toolkits_olddrspec.egg-info/SOURCES.txt
lsl_toolkits_olddrspec.egg-info/dependency_links.txt
lsl_toolkits_olddrspec.egg-info/namespace_packages.txt
lsl_toolkits_olddrspec.egg-info/not-zip-safe
lsl_toolkits_olddrspec.egg-info/requires.txt
lsl_toolkits_olddrspec.egg-info/top_level.txt
tests/__init__.py
tests/test_drspec.py
tests/data/drspec-test.dat