Metadata-Version: 1.2
Name: lsl-toolkits-olddrspec
Version: 0.2.2
Summary: LSL Toolkit for Older LWA DR Spectrometer Data
Home-page: https://fornax.phys.unm.edu/lwa/trac/
Author: Jayce Dowell
Author-email: jdowell@unm.edu
License: GPL
Platform: UNKNOWN
Classifier: Development Status :: 7 - Inactive
Classifier: Intended Audience :: Developers
Classifier: Intended Audience :: Science/Research
Classifier: License :: OSI Approved :: GNU General Public License (GPL)
Classifier: Topic :: Scientific/Engineering :: Astronomy
Classifier: Programming Language :: Python :: 2
Classifier: Programming Language :: Python :: 2.6
Classifier: Programming Language :: Python :: 2.7
Classifier: Operating System :: MacOS :: MacOS X
Classifier: Operating System :: POSIX :: Linux
Requires-Python: >=2.6, <3
